[
  {
    "ContainingType": "VirtualShop.CartApi.Controllers.CartController",
    "Method": "AddCart",
    "RelativePath": "api/Cart/addcart",
    "HttpMethod": "POST",
    "IsController": true,
    "Order": 0,
    "Parameters": [
      {
        "Name": "cartDto",
        "Type": "VirtualShop.CartApi.DTOs.CartDTO",
        "IsRequired": true
      }
    ],
    "ReturnTypes": [
      {
        "Type": "VirtualShop.CartApi.DTOs.CartDTO",
        "MediaTypes": [
          "text/plain",
          "application/json",
          "text/json"
        ],
        "StatusCode": 200
      }
    ]
  },
  {
    "ContainingType": "VirtualShop.CartApi.Controllers.CartController",
    "Method": "DeleteCart",
    "RelativePath": "api/Cart/deletecart/{id}",
    "HttpMethod": "DELETE",
    "IsController": true,
    "Order": 0,
    "Parameters": [
      {
        "Name": "id",
        "Type": "System.Int32",
        "IsRequired": true
      }
    ],
    "ReturnTypes": [
      {
        "Type": "System.Boolean",
        "MediaTypes": [
          "text/plain",
          "application/json",
          "text/json"
        ],
        "StatusCode": 200
      }
    ]
  },
  {
    "ContainingType": "VirtualShop.CartApi.Controllers.CartController",
    "Method": "GetByUserId",
    "RelativePath": "api/Cart/getcart/{userid}",
    "HttpMethod": "GET",
    "IsController": true,
    "Order": 0,
    "Parameters": [
      {
        "Name": "userid",
        "Type": "System.String",
        "IsRequired": true
      }
    ],
    "ReturnTypes": [
      {
        "Type": "VirtualShop.CartApi.DTOs.CartDTO",
        "MediaTypes": [
          "text/plain",
          "application/json",
          "text/json"
        ],
        "StatusCode": 200
      }
    ]
  },
  {
    "ContainingType": "VirtualShop.CartApi.Controllers.CartController",
    "Method": "UpdateCart",
    "RelativePath": "api/Cart/updatecart",
    "HttpMethod": "PUT",
    "IsController": true,
    "Order": 0,
    "Parameters": [
      {
        "Name": "cartDto",
        "Type": "VirtualShop.CartApi.DTOs.CartDTO",
        "IsRequired": true
      }
    ],
    "ReturnTypes": [
      {
        "Type": "VirtualShop.CartApi.DTOs.CartDTO",
        "MediaTypes": [
          "text/plain",
          "application/json",
          "text/json"
        ],
        "StatusCode": 200
      }
    ]
  }
]